astrocut/__init__.py
astrocut/_astropy_init.py
astrocut/asdf_cutout.py
astrocut/conftest.py
astrocut/cube_cutout.py
astrocut/cube_factory.py
astrocut/cutout.py
astrocut/cutout_factory.py
astrocut/cutout_processing.py
astrocut/exceptions.py
astrocut/fits_cutout.py
astrocut/footprint_cutout.py
astrocut/image_cutout.py
astrocut/tess_cube_cutout.py
astrocut/tess_footprint_cutout.py
astrocut/tica_cube_factory.py
astrocut/version.py
astrocut/extern/__init__.py
astrocut/tests/__init__.py
astrocut/tests/setup_package.py
astrocut/tests/test_asdf_cutout.py
astrocut/tests/test_cube_cut.py
astrocut/tests/test_cube_factory.py
astrocut/tests/test_cutout_processing.py
astrocut/tests/test_cutouts.py
astrocut/tests/test_fits_cutout.py
astrocut/tests/test_image_cutout.py
astrocut/tests/test_tess_cube_cutout.py
astrocut/tests/test_tess_footprint_cutout.py
astrocut/tests/test_utils.py
astrocut/tests/utils_for_test.py
astrocut/tests/data/ex_ffi_wcs.txt
astrocut/utils/__init__.py
astrocut/utils/logger.py
astrocut/utils/utils.py
astrocut/utils/wcs_fitting.py
astrocut/utils/tests/__init__.py
astrocut-1.1.0.dist-info/licenses/licenses/LICENSE.rst
astrocut-1.1.0.dist-info/METADATA
astrocut-1.1.0.dist-info/WHEEL
astrocut-1.1.0.dist-info/entry_points.txt
astrocut-1.1.0.dist-info/top_level.txt
astrocut-1.1.0.dist-info/RECORD
