Metadata-Version: 2.4
Name: astrocut
Version: 1.1.0
Summary: Cutout tools for astronomical images
Home-page: https://astrocut.readthedocs.io
Author: MAST Archive Developers
Author-email: archive@stsci.edu
License: BSD 3-Clause
Requires-Python: >=3.9
License-File: licenses/LICENSE.rst
Requires-Dist: asdf>=4.1.0
Requires-Dist: astropy>=5.2
Requires-Dist: cachetools>=5.3.2
Requires-Dist: fsspec[http]>=2022.8.2
Requires-Dist: s3fs>=2022.8.2
Requires-Dist: s3path>=0.5.7
Requires-Dist: roman_datamodels>=0.19.0
Requires-Dist: requests>=2.32.3
Requires-Dist: spherical_geometry>=1.3.0
Requires-Dist: gwcs>=0.21.0
Requires-Dist: scipy
Requires-Dist: Pillow
Provides-Extra: test
Requires-Dist: pytest-astropy; extra == "test"
Requires-Dist: astroquery>=0.4.6; extra == "test"
Provides-Extra: docs
Requires-Dist: sphinx!=4.1.0; extra == "docs"
Requires-Dist: docutils==0.16; extra == "docs"
Requires-Dist: sphinx-astropy; extra == "docs"
Requires-Dist: sphinx_rtd_theme>=0.5.2; extra == "docs"
Dynamic: description
Dynamic: description-content-type
Dynamic: license-file
